LICENSE
README.md
setup.cfg
setup.py
caafinder/__init__.py
meta_wmy_d1.egg-info/PKG-INFO
meta_wmy_d1.egg-info/SOURCES.txt
meta_wmy_d1.egg-info/dependency_links.txt
meta_wmy_d1.egg-info/top_level.txt