Metadata-Version: 2.1
Name: meta-wmy-d1
Version: 0.1.5
Summary: 手写python库
Home-page: https://github.com/Gutier14/CAAFinder
Author: mingyu.wang
Author-email: mingyu.wang@appshahe.com
License: MIT License
Keywords: MetaApp
Platform: any
License-File: LICENSE
